{
  "artist": "Lil Mosey",
  "overall_vad": {
    "valence": 2.64,
    "arousal": 3.72,
    "dominance": 3.51
  },
  "chunked_vad": [
    {
      "chunk_id": 1,
      "lyrics_text": "One bad bitch, and she do what I say so Two big .40s and a big ass Draco (two, boom, boom) Three more millions when you ask how my day go Poured up a 4, now that's blueberry Faygo",
      "valence": 2.79,
      "arousal": 3.6,
      "dominance": 3.3
    },
    {
      "chunk_id": 2,
      "lyrics_text": "Two big .40s and a big ass Draco (two, boom, boom) Three more millions when you ask how my day go Poured up a 4, now that's blueberry Faygo One false move, and we straight to shooting shit",
      "valence": 3.0,
      "arousal": 3.74,
      "dominance": 3.36
    },
    {
      "chunk_id": 3,
      "lyrics_text": "Three more millions when you ask how my day go Poured up a 4, now that's blueberry Faygo One false move, and we straight to shooting shit Two small bands just to take you out real quick (bands)",
      "valence": 3.12,
      "arousal": 3.5,
      "dominance": 3.35
    },
    {
      "chunk_id": 4,
      "lyrics_text": "Poured up a 4, now that's blueberry Faygo One false move, and we straight to shooting shit Two small bands just to take you out real quick (bands) Three more hoes, pull up, I'm fucking shit",
      "valence": 2.33,
      "arousal": 4.0,
      "dominance": 3.4
    },
    {
      "chunk_id": 5,
      "lyrics_text": "One false move, and we straight to shooting shit Two small bands just to take you out real quick (bands) Three more hoes, pull up, I'm fucking shit That's how it go, big bands, I'm thumbin' shit (that's how it goes)",
      "valence": 2.37,
      "arousal": 3.9,
      "dominance": 3.45
    },
    {
      "chunk_id": 6,
      "lyrics_text": "Two small bands just to take you out real quick (bands) Three more hoes, pull up, I'm fucking shit That's how it go, big bands, I'm thumbin' shit (that's how it goes) One bad bitch, and she do what I say so (yeah, gang)",
      "valence": 2.37,
      "arousal": 3.76,
      "dominance": 3.48
    },
    {
      "chunk_id": 7,
      "lyrics_text": "Three more hoes, pull up, I'm fucking shit That's how it go, big bands, I'm thumbin' shit (that's how it goes) One bad bitch, and she do what I say so (yeah, gang) Two big .40s and a big ass Draco (two)",
      "valence": 2.36,
      "arousal": 3.84,
      "dominance": 3.57
    },
    {
      "chunk_id": 8,
      "lyrics_text": "That's how it go, big bands, I'm thumbin' shit (that's how it goes) One bad bitch, and she do what I say so (yeah, gang) Two big .40s and a big ass Draco (two) Three more millions when you ask how my day go",
      "valence": 2.93,
      "arousal": 3.5,
      "dominance": 3.32
    },
    {
      "chunk_id": 9,
      "lyrics_text": "One bad bitch, and she do what I say so (yeah, gang) Two big .40s and a big ass Draco (two) Three more millions when you ask how my day go Poured up a 4, now that's blueberry Faygo",
      "valence": 2.92,
      "arousal": 3.6,
      "dominance": 3.34
    },
    {
      "chunk_id": 10,
      "lyrics_text": "Two big .40s and a big ass Draco (two) Three more millions when you ask how my day go Poured up a 4, now that's blueberry Faygo One false move, and we straight to shooting shit",
      "valence": 3.08,
      "arousal": 3.64,
      "dominance": 3.36
    },
    {
      "chunk_id": 11,
      "lyrics_text": "Three more millions when you ask how my day go Poured up a 4, now that's blueberry Faygo One false move, and we straight to shooting shit Two small bands just to take you out real quick (bands)",
      "valence": 3.12,
      "arousal": 3.5,
      "dominance": 3.35
    },
    {
      "chunk_id": 12,
      "lyrics_text": "Poured up a 4, now that's blueberry Faygo One false move, and we straight to shooting shit Two small bands just to take you out real quick (bands) Three more hoes, pull up, I'm fucking shit",
      "valence": 2.33,
      "arousal": 4.0,
      "dominance": 3.4
    },
    {
      "chunk_id": 13,
      "lyrics_text": "One false move, and we straight to shooting shit Two small bands just to take you out real quick (bands) Three more hoes, pull up, I'm fucking shit That's how it go, big bands, I'm thumbin' shit",
      "valence": 2.37,
      "arousal": 3.92,
      "dominance": 3.47
    },
    {
      "chunk_id": 14,
      "lyrics_text": "Two small bands just to take you out real quick (bands) Three more hoes, pull up, I'm fucking shit That's how it go, big bands, I'm thumbin' shit I'm with my niggas yeah, we some rockstars",
      "valence": 2.76,
      "arousal": 3.96,
      "dominance": 3.49
    },
    {
      "chunk_id": 15,
      "lyrics_text": "Three more hoes, pull up, I'm fucking shit That's how it go, big bands, I'm thumbin' shit I'm with my niggas yeah, we some rockstars And I'm with my nigga yeah, KK Wokhardt (KK Wokhardt)",
      "valence": 2.69,
      "arousal": 3.99,
      "dominance": 3.57
    },
    {
      "chunk_id": 16,
      "lyrics_text": "That's how it go, big bands, I'm thumbin' shit I'm with my niggas yeah, we some rockstars And I'm with my nigga yeah, KK Wokhardt (KK Wokhardt) This not my dick, lil' bitch, my Glock hard (lil' bitch)",
      "valence": 2.72,
      "arousal": 3.65,
      "dominance": 3.65
    },
    {
      "chunk_id": 17,
      "lyrics_text": "I'm with my niggas yeah, we some rockstars And I'm with my nigga yeah, KK Wokhardt (KK Wokhardt) This not my dick, lil' bitch, my Glock hard (lil' bitch) Straight to the cash, I'm a trapstar (cash)",
      "valence": 3.11,
      "arousal": 3.6,
      "dominance": 3.68
    },
    {
      "chunk_id": 18,
      "lyrics_text": "And I'm with my nigga yeah, KK Wokhardt (KK Wokhardt) This not my dick, lil' bitch, my Glock hard (lil' bitch) Straight to the cash, I'm a trapstar (cash) Straight to the bag, I'm that nigga, huh (bag, oh)",
      "valence": 2.65,
      "arousal": 3.55,
      "dominance": 3.74
    },
    {
      "chunk_id": 19,
      "lyrics_text": "This not my dick, lil' bitch, my Glock hard (lil' bitch) Straight to the cash, I'm a trapstar (cash) Straight to the bag, I'm that nigga, huh (bag, oh) Got me some gas, rollin' up some",
      "valence": 2.35,
      "arousal": 3.61,
      "dominance": 3.82
    },
    {
      "chunk_id": 20,
      "lyrics_text": "Straight to the cash, I'm a trapstar (cash) Straight to the bag, I'm that nigga, huh (bag, oh) Got me some gas, rollin' up some Fft, fft, cash, yeah, I got me some",
      "valence": 3.03,
      "arousal": 3.29,
      "dominance": 3.58
    },
    {
      "chunk_id": 21,
      "lyrics_text": "Straight to the bag, I'm that nigga, huh (bag, oh) Got me some gas, rollin' up some Fft, fft, cash, yeah, I got me some I ain't fucked her yesterday (yeah)",
      "valence": 2.89,
      "arousal": 3.38,
      "dominance": 3.64
    },
    {
      "chunk_id": 22,
      "lyrics_text": "Got me some gas, rollin' up some Fft, fft, cash, yeah, I got me some I ain't fucked her yesterday (yeah) I'ma fuck some",
      "valence": 2.73,
      "arousal": 3.67,
      "dominance": 3.76
    },
    {
      "chunk_id": 23,
      "lyrics_text": "Fft, fft, cash, yeah, I got me some I ain't fucked her yesterday (yeah) I'ma fuck some One bad bitch, and she do what I say so (one, gang)",
      "valence": 2.28,
      "arousal": 3.75,
      "dominance": 3.81
    },
    {
      "chunk_id": 24,
      "lyrics_text": "I ain't fucked her yesterday (yeah) I'ma fuck some One bad bitch, and she do what I say so (one, gang) Two big .40s and a big ass Draco (two, boom, boom)",
      "valence": 2.29,
      "arousal": 3.76,
      "dominance": 3.8
    },
    {
      "chunk_id": 25,
      "lyrics_text": "I'ma fuck some One bad bitch, and she do what I say so (one, gang) Two big .40s and a big ass Draco (two, boom, boom) Three more millions when you ask how my day go",
      "valence": 2.52,
      "arousal": 3.84,
      "dominance": 3.51
    },
    {
      "chunk_id": 26,
      "lyrics_text": "One bad bitch, and she do what I say so (one, gang) Two big .40s and a big ass Draco (two, boom, boom) Three more millions when you ask how my day go Poured up a 4, now that's blueberry Faygo",
      "valence": 2.84,
      "arousal": 3.64,
      "dominance": 3.41
    },
    {
      "chunk_id": 27,
      "lyrics_text": "Two big .40s and a big ass Draco (two, boom, boom) Three more millions when you ask how my day go Poured up a 4, now that's blueberry Faygo One false move, and we straight to shooting shit",
      "valence": 3.0,
      "arousal": 3.74,
      "dominance": 3.36
    },
    {
      "chunk_id": 28,
      "lyrics_text": "Three more millions when you ask how my day go Poured up a 4, now that's blueberry Faygo One false move, and we straight to shooting shit Two small bands just to take you out real quick (bands)",
      "valence": 3.12,
      "arousal": 3.5,
      "dominance": 3.35
    },
    {
      "chunk_id": 29,
      "lyrics_text": "Poured up a 4, now that's blueberry Faygo One false move, and we straight to shooting shit Two small bands just to take you out real quick (bands) Three more hoes, pull up, I'm fucking shit (three more, gang)",
      "valence": 2.34,
      "arousal": 3.98,
      "dominance": 3.52
    },
    {
      "chunk_id": 30,
      "lyrics_text": "One false move, and we straight to shooting shit Two small bands just to take you out real quick (bands) Three more hoes, pull up, I'm fucking shit (three more, gang) That's how it go, big bands, I'm thumbin' shit (that's how it goes)",
      "valence": 2.39,
      "arousal": 3.77,
      "dominance": 3.54
    },
    {
      "chunk_id": 31,
      "lyrics_text": "Two small bands just to take you out real quick (bands) Three more hoes, pull up, I'm fucking shit (three more, gang) That's how it go, big bands, I'm thumbin' shit (that's how it goes) 3-0 clip in my Nina (oh, oh)",
      "valence": 2.5,
      "arousal": 3.8,
      "dominance": 3.54
    },
    {
      "chunk_id": 32,
      "lyrics_text": "Three more hoes, pull up, I'm fucking shit (three more, gang) That's how it go, big bands, I'm thumbin' shit (that's how it goes) 3-0 clip in my Nina (oh, oh) On my toes, Gucci, Valentino (yeah, bitch)",
      "valence": 2.36,
      "arousal": 3.97,
      "dominance": 3.71
    },
    {
      "chunk_id": 33,
      "lyrics_text": "That's how it go, big bands, I'm thumbin' shit (that's how it goes) 3-0 clip in my Nina (oh, oh) On my toes, Gucci, Valentino (yeah, bitch) She on go, your bitch fuck the team, uh (lil' bitch)",
      "valence": 2.36,
      "arousal": 3.82,
      "dominance": 3.72
    },
    {
      "chunk_id": 34,
      "lyrics_text": "3-0 clip in my Nina (oh, oh) On my toes, Gucci, Valentino (yeah, bitch) She on go, your bitch fuck the team, uh (lil' bitch) 'Cause you know your bitch want a winner (winner)",
      "valence": 2.64,
      "arousal": 3.86,
      "dominance": 3.72
    },
    {
      "chunk_id": 35,
      "lyrics_text": "On my toes, Gucci, Valentino (yeah, bitch) She on go, your bitch fuck the team, uh (lil' bitch) 'Cause you know your bitch want a winner (winner) I just went back to my city (to my city)",
      "valence": 2.28,
      "arousal": 3.9,
      "dominance": 3.91
    },
    {
      "chunk_id": 36,
      "lyrics_text": "She on go, your bitch fuck the team, uh (lil' bitch) 'Cause you know your bitch want a winner (winner) I just went back to my city (to my city) And you know they all fuckin' with me (big hands)",
      "valence": 2.1,
      "arousal": 3.91,
      "dominance": 3.87
    },
    {
      "chunk_id": 37,
      "lyrics_text": "'Cause you know your bitch want a winner (winner) I just went back to my city (to my city) And you know they all fuckin' with me (big hands) But it ain't safe, hoes with me (hoes)",
      "valence": 2.32,
      "arousal": 3.73,
      "dominance": 3.26
    },
    {
      "chunk_id": 38,
      "lyrics_text": "I just went back to my city (to my city) And you know they all fuckin' with me (big hands) But it ain't safe, hoes with me (hoes) I'ma chase bands 'til they end me",
      "valence": 2.39,
      "arousal": 3.58,
      "dominance": 2.96
    },
    {
      "chunk_id": 39,
      "lyrics_text": "And you know they all fuckin' with me (big hands) But it ain't safe, hoes with me (hoes) I'ma chase bands 'til they end me One bad bitch, and she do what I say so (one, gang)",
      "valence": 2.29,
      "arousal": 3.59,
      "dominance": 3.44
    },
    {
      "chunk_id": 40,
      "lyrics_text": "But it ain't safe, hoes with me (hoes) I'ma chase bands 'til they end me One bad bitch, and she do what I say so (one, gang) Two big .40s and a big ass Draco (two, boom, boom)",
      "valence": 2.39,
      "arousal": 3.69,
      "dominance": 3.52
    },
    {
      "chunk_id": 41,
      "lyrics_text": "I'ma chase bands 'til they end me One bad bitch, and she do what I say so (one, gang) Two big .40s and a big ass Draco (two, boom, boom) Three more millions when you ask how my day go",
      "valence": 2.77,
      "arousal": 3.65,
      "dominance": 3.5
    },
    {
      "chunk_id": 42,
      "lyrics_text": "One bad bitch, and she do what I say so (one, gang) Two big .40s and a big ass Draco (two, boom, boom) Three more millions when you ask how my day go Poured up a 4, now that's blueberry Faygo",
      "valence": 2.84,
      "arousal": 3.64,
      "dominance": 3.41
    },
    {
      "chunk_id": 43,
      "lyrics_text": "Two big .40s and a big ass Draco (two, boom, boom) Three more millions when you ask how my day go Poured up a 4, now that's blueberry Faygo One false move, and we straight to shooting shit",
      "valence": 3.0,
      "arousal": 3.74,
      "dominance": 3.36
    },
    {
      "chunk_id": 44,
      "lyrics_text": "Three more millions when you ask how my day go Poured up a 4, now that's blueberry Faygo One false move, and we straight to shooting shit Two small bands just to take you out real quick (bands)",
      "valence": 3.12,
      "arousal": 3.5,
      "dominance": 3.35
    },
    {
      "chunk_id": 45,
      "lyrics_text": "Poured up a 4, now that's blueberry Faygo One false move, and we straight to shooting shit Two small bands just to take you out real quick (bands) Three more hoes, pull up, I'm fucking shit (three more, gang)",
      "valence": 2.34,
      "arousal": 3.98,
      "dominance": 3.52
    },
    {
      "chunk_id": 46,
      "lyrics_text": "One false move, and we straight to shooting shit Two small bands just to take you out real quick (bands) Three more hoes, pull up, I'm fucking shit (three more, gang) That's how it go, big bands, I'm thumbin' shit (that's how it goes)",
      "valence": 2.39,
      "arousal": 3.77,
      "dominance": 3.54
    },
    {
      "chunk_id": 47,
      "lyrics_text": "Two small bands just to take you out real quick (bands) Three more hoes, pull up, I'm fucking shit (three more, gang) That's how it go, big bands, I'm thumbin' shit (that's how it goes) One bad bitch, and she do what I say so (yeah, gang)",
      "valence": 2.38,
      "arousal": 3.75,
      "dominance": 3.51
    },
    {
      "chunk_id": 48,
      "lyrics_text": "Three more hoes, pull up, I'm fucking shit (three more, gang) That's how it go, big bands, I'm thumbin' shit (that's how it goes) One bad bitch, and she do what I say so (yeah, gang) Two big .40s and a big ass Draco (two)",
      "valence": 2.31,
      "arousal": 3.8,
      "dominance": 3.7
    },
    {
      "chunk_id": 49,
      "lyrics_text": "That's how it go, big bands, I'm thumbin' shit (that's how it goes) One bad bitch, and she do what I say so (yeah, gang) Two big .40s and a big ass Draco (two) Three more millions when you ask how my day go",
      "valence": 2.93,
      "arousal": 3.5,
      "dominance": 3.32
    },
    {
      "chunk_id": 50,
      "lyrics_text": "One bad bitch, and she do what I say so (yeah, gang) Two big .40s and a big ass Draco (two) Three more millions when you ask how my day go Poured up a 4, now that's blueberry Faygo",
      "valence": 2.92,
      "arousal": 3.6,
      "dominance": 3.34
    },
    {
      "chunk_id": 51,
      "lyrics_text": "Two big .40s and a big ass Draco (two) Three more millions when you ask how my day go Poured up a 4, now that's blueberry Faygo One false move, and we straight to shooting shit",
      "valence": 3.08,
      "arousal": 3.64,
      "dominance": 3.36
    },
    {
      "chunk_id": 52,
      "lyrics_text": "Three more millions when you ask how my day go Poured up a 4, now that's blueberry Faygo One false move, and we straight to shooting shit Two small bands just to take you out real quick (bands)",
      "valence": 3.12,
      "arousal": 3.5,
      "dominance": 3.35
    },
    {
      "chunk_id": 53,
      "lyrics_text": "Poured up a 4, now that's blueberry Faygo One false move, and we straight to shooting shit Two small bands just to take you out real quick (bands) Three more hoes, pull up, I'm fucking shit (three, yeah)",
      "valence": 2.39,
      "arousal": 4.03,
      "dominance": 3.5
    },
    {
      "chunk_id": 54,
      "lyrics_text": "One false move, and we straight to shooting shit Two small bands just to take you out real quick (bands) Three more hoes, pull up, I'm fucking shit (three, yeah) That's how it go, big bands, I'm thumbin' shit (yeah)",
      "valence": 2.43,
      "arousal": 3.89,
      "dominance": 3.54
    }
  ]
}